boerse_frankfurt_api/__init__.py
boerse_frankfurt_api/api.py
boerse_frankfurt_api/finanzen_zero.py
boerse_frankfurt_api-1.0.0.dist-info/WHEEL
boerse_frankfurt_api-1.0.0.dist-info/METADATA
boerse_frankfurt_api-1.0.0.dist-info/RECORD
