Metadata-Version: 2.1
Name: boerse-frankfurt-api
Version: 1.0.0
Summary: 
Author: Martin Marmsoler
Author-email: martin.marmsoler@gmail.com
Requires-Python: >=3.9,<4.0
Classifier: Programming Language :: Python :: 3
Classifier: Programming Language :: Python :: 3.9
Classifier: Programming Language :: Python :: 3.10
Requires-Dist: requests (==2.28.1)
